ctc_score/__init__.py
ctc_score/configs.py
ctc_score/dialog_scorer.py
ctc_score/download.py
ctc_score/factual_consistency_scorer.py
ctc_score/scorer.py
ctc_score/style_transfer_scorer.py
ctc_score/summarization_scorer.py
ctc_score/data_utils/__init__.py
ctc_score/data_utils/data_utils.py
ctc_score/models/__init__.py
ctc_score/models/aligner.py
ctc_score/models/bert_aligner.py
ctc_score/models/bleurt_aligner.py
ctc_score/models/bleurt_aligner_pt.py
ctc_score/models/discriminative_aligner.py
ctc_score_cli/__init__.py
ctc_score_cli/score.py
ctc_score-0.1.3.dist-info/LICENSE
ctc_score-0.1.3.dist-info/METADATA
ctc_score-0.1.3.dist-info/WHEEL
ctc_score-0.1.3.dist-info/entry_points.txt
ctc_score-0.1.3.dist-info/top_level.txt
ctc_score-0.1.3.dist-info/RECORD
