Metadata-Version: 2.1
Name: ctc-score
Version: 0.1.3
Summary: CTC: A Unified Framework for Evaluating Natural Language Generation
Home-page: https://github.com/tanyuqian/ctc-gen-eval
Author: Mingkai Deng*, Bowen Tan*, Zhengzhong Liu, Eric P. Xing, Zhiting Hu, Yuheng Zha(maintainer)
License: MIT
Keywords: CTC Score
Classifier: Intended Audience :: Science/Research
Classifier: License :: OSI Approved :: MIT License
Classifier: Programming Language :: Python :: 3
Classifier: Topic :: Scientific/Engineering :: Artificial Intelligence
Requires-Python: >=3.6
License-File: LICENSE
Requires-Dist: nltk
Requires-Dist: transformers (>=4.3)
Requires-Dist: datasets (>=1.5)
Requires-Dist: cleantext
Requires-Dist: bert-score (>=0.3)
